short_language_detection/__init__.py
short_language_detection/constants.py
short_language_detection/detector.py
short_language_detection/dict_detector.py
short_language_detection/fasttext_detector.py
short_language_detection/lingua_detector.py
short_language_detection/main_detector.py
short_language_detection/output_formater.py
short_language_detection/py.typed
short_language_detection/data/top_languages.json
short_language_detection/data/dictionaries/ar.txt
short_language_detection/data/dictionaries/bg.txt
short_language_detection/data/dictionaries/ca.txt
short_language_detection/data/dictionaries/cs.txt
short_language_detection/data/dictionaries/da.txt
short_language_detection/data/dictionaries/de.txt
short_language_detection/data/dictionaries/el.txt
short_language_detection/data/dictionaries/en.txt
short_language_detection/data/dictionaries/es.txt
short_language_detection/data/dictionaries/fi.txt
short_language_detection/data/dictionaries/fr.txt
short_language_detection/data/dictionaries/hi.txt
short_language_detection/data/dictionaries/hu.txt
short_language_detection/data/dictionaries/id.txt
short_language_detection/data/dictionaries/it.txt
short_language_detection/data/dictionaries/nb.txt
short_language_detection/data/dictionaries/nl.txt
short_language_detection/data/dictionaries/pl.txt
short_language_detection/data/dictionaries/pt.txt
short_language_detection/data/dictionaries/ro.txt
short_language_detection/data/dictionaries/ru.txt
short_language_detection/data/dictionaries/sk.txt
short_language_detection/data/dictionaries/sv.txt
short_language_detection/data/dictionaries/tr.txt
short_language_detection/data/dictionaries/uk.txt
short_language_detection/data/dictionaries/vi.txt
short_language_detection/weights/discord_langdetect.ftz
short_language_detection/weights/langdetect.ftz
short_language_detection/weights/lid.176.ftz
short_language_detection-0.1.9.dist-info/METADATA
short_language_detection-0.1.9.dist-info/WHEEL
short_language_detection-0.1.9.dist-info/licenses/LICENSE
short_language_detection-0.1.9.dist-info/RECORD
