Metadata-Version: 2.4
Name: short-language-detection
Version: 0.1.9
Summary: A simple language detection library for short texts.
Author-email: jourdelune <jourdelune863@gmail.com>
License-Expression: MIT
License-File: LICENSE
Requires-Python: >=3.10
Requires-Dist: black>=25.1.0
Requires-Dist: emoji>=2.14.1
Requires-Dist: fasttext-wheel>=0.9.2
Requires-Dist: isort>=6.0.1
Requires-Dist: lingua-language-detector>=2.0.2
Requires-Dist: numpy==1.26.4
Requires-Dist: pytest-timeout>=2.3.1
Requires-Dist: pytest>=8.3.4
